zvt/__init__.py
zvt/consts.py
zvt/fill_project.py
zvt/main.py
zvt/plugin.py
zvt/zvt_server.py
zvt/api/__init__.py
zvt/api/intent.py
zvt/api/kdata.py
zvt/api/portfolio.py
zvt/api/selector.py
zvt/api/stats.py
zvt/api/utils.py
zvt/autocode/__init__.py
zvt/autocode/generator.py
zvt/autocode/templates/.coveragerc.template
zvt/autocode/templates/.gitignore.template
zvt/autocode/templates/.travis.yml.template
zvt/autocode/templates/LICENSE.template
zvt/autocode/templates/MANIFEST.in.template
zvt/autocode/templates/README-en.md.template
zvt/autocode/templates/README.md.template
zvt/autocode/templates/__init__.py
zvt/autocode/templates/fill_project.py.template
zvt/autocode/templates/kdata_common.py.template
zvt/autocode/templates/kdata_recorder.py.template
zvt/autocode/templates/meta.py.template
zvt/autocode/templates/meta_recorder.py.template
zvt/autocode/templates/pkg_init.py.template
zvt/autocode/templates/requirements.txt.template
zvt/autocode/templates/setup.py.template
zvt/autocode/templates/test_pass.py.template
zvt/broker/__init__.py
zvt/broker/qmt/__init__.py
zvt/broker/qmt/context.py
zvt/broker/qmt/errors.py
zvt/broker/qmt/qmt_account.py
zvt/broker/qmt/qmt_quote.py
zvt/common/__init__.py
zvt/common/query_models.py
zvt/common/trading_models.py
zvt/contract/__init__.py
zvt/contract/api.py
zvt/contract/base_service.py
zvt/contract/context.py
zvt/contract/data_type.py
zvt/contract/drawer.py
zvt/contract/factor.py
zvt/contract/model.py
zvt/contract/normal_data.py
zvt/contract/reader.py
zvt/contract/recorder.py
zvt/contract/register.py
zvt/contract/schema.py
zvt/contract/utils.py
zvt/contract/zvt_info.py
zvt/domain/__init__.py
zvt/domain/actor/__init__.py
zvt/domain/actor/actor_meta.py
zvt/domain/actor/stock_actor.py
zvt/domain/emotion/__init__.py
zvt/domain/emotion/emotion.py
zvt/domain/fundamental/__init__.py
zvt/domain/fundamental/dividend_financing.py
zvt/domain/fundamental/finance.py
zvt/domain/fundamental/trading.py
zvt/domain/fundamental/valuation.py
zvt-0.13.5.dist-info/licenses/LICENSE
zvt-0.13.5.dist-info/METADATA
zvt-0.13.5.dist-info/WHEEL
zvt-0.13.5.dist-info/entry_points.txt
zvt-0.13.5.dist-info/top_level.txt
zvt-0.13.5.dist-info/RECORD
