Metadata-Version: 2.4
Name: zvt
Version: 0.13.5
Summary: unified,modular quant framework for human beings 
Home-page: https://github.com/zvtvz/zvt
Author: foolcage
Author-email: 5533061@qq.com
Project-URL: Bug Reports, https://github.com/zvtvz/zvt/issues
Project-URL: Funding, https://www.foolcage.com/zvt
Project-URL: Say Thanks!, https://saythanks.io/to/foolcage
Project-URL: Source, https://github.com/zvtvz/zvt
Keywords: quant stock finance fintech big-data zvt technical-analysis trading-platform pandas fundamental-analysis
Classifier: Development Status :: 5 - Production/Stable
Classifier: Intended Audience :: Developers
Classifier: Intended Audience :: Customer Service
Classifier: Intended Audience :: Education
Classifier: Intended Audience :: Financial and Insurance Industry
Classifier: Topic :: Software Development :: Build Tools
Classifier: Topic :: Office/Business :: Financial :: Investment
Classifier: License :: OSI Approved :: MIT License
Classifier: Programming Language :: Python :: 3.9
Classifier: Programming Language :: Python :: 3.10
Classifier: Programming Language :: Python :: 3.11
Classifier: Programming Language :: Python :: 3.12
Requires-Python: >=3.9, <4
License-File: LICENSE
Requires-Dist: requests==2.32.0
Requires-Dist: SQLAlchemy==2.0.36
Requires-Dist: pandas==2.2.3
Requires-Dist: pydantic==2.6.4
Requires-Dist: arrow==1.3.0
Requires-Dist: openpyxl==3.1.1
Requires-Dist: demjson3==3.0.6
Requires-Dist: plotly==5.13.0
Requires-Dist: dash==2.18.2
Requires-Dist: jqdatapy==0.1.8
Requires-Dist: dash-bootstrap-components==1.3.1
Requires-Dist: dash_daq==0.5.0
Requires-Dist: scikit-learn==1.5.2
Requires-Dist: fastapi==0.110.0
Requires-Dist: fastapi-pagination==0.12.23
Requires-Dist: apscheduler==3.10.4
Requires-Dist: eastmoneypy==0.2.0
Requires-Dist: orjson==3.10.3
Requires-Dist: numpy==2.1.3
Dynamic: author
Dynamic: author-email
Dynamic: classifier
Dynamic: description
Dynamic: description-content-type
Dynamic: home-page
Dynamic: keywords
Dynamic: license-file
Dynamic: project-url
Dynamic: requires-dist
Dynamic: requires-python
Dynamic: summary
